{
  "schema_version": "1.0",
  "product_key": "private-link",
  "display_name": "Azure 专用链接定价",
  "slug": "private-link",
  "page_model": "FlexibleContentPage",
  "capability_status": "supported",
  "catalog_categories": [
    "networking"
  ],
  "sources": {
    "zh-cn": {
      "availability": "available",
      "snapshot_path": "pricing/details/private-link/index.html",
      "url": "https://www.azure.cn/pricing/details/private-link/"
    },
    "en-us": {
      "availability": "available",
      "snapshot_path": "pricing/details/private-link/index.html",
      "url": "https://www.azure.cn/en-us/pricing/details/private-link/"
    }
  },
  "extraction": {
    "important_section_titles": [
      "定价详细信息",
      "定价详情",
      "pricing details",
      "常见问题",
      "faq",
      "frequently asked questions",
      "支持和服务级别协议"
    ],
    "estimated_size_mb": 1.0,
    "priority_sections": [
      "pricing-tables",
      "banner",
      "description",
      "faq"
    ],
    "enable_region_processing": true
  },
  "quality": {
    "min_content_length": 100
  }
}
